README.md
setup.py
biget/__init__.py
biget/video.py
biget.egg-info/PKG-INFO
biget.egg-info/SOURCES.txt
biget.egg-info/dependency_links.txt
biget.egg-info/requires.txt
biget.egg-info/top_level.txt
biget/vtools/__init__.py
biget/vtools/downloader.py
biget/vtools/headers.py
biget/vtools/utils.py
error/__init__.py
error/cc_exception.py
error/warn.py
utils/__init__.py
utils/cc_tool.py
utils/pyffmpeg.py
utils/pypyth.py