Metadata-Version: 2.1
Name: biget
Version: 0.1.0
Summary: 关于B站的一个爬虫，可以获取视频的信息，下载视频等
Home-page: https://github.com/ujay-zheng/biget
Author: ujay
Author-email: 897013045@qq.com
License: UNKNOWN
Keywords: pip,bilibili,video download,spider,B站视频下载,弹幕
Platform: any
